LICENSE
README.md
setup.py
PyTube_Frontend.egg-info/PKG-INFO
PyTube_Frontend.egg-info/SOURCES.txt
PyTube_Frontend.egg-info/dependency_links.txt
PyTube_Frontend.egg-info/requires.txt
PyTube_Frontend.egg-info/top_level.txt
pytube_frontend/__init__.py
pytube_frontend/download_functions.py
pytube_frontend/downloader.py
pytube_frontend/ffmpeg_functions.py
pytube_frontend/streams.py
pytube_frontend/video_info.py