Metadata-Version: 2.1
Name: PyTube-Frontend
Version: 0.0.2
Summary: Frontend for PyTube
Author: ewbrowntech (Ethan Brown)
Author-email: <ewbrowntech@gmail.com>
Keywords: python,pytube,API
Classifier: Development Status :: 4 - Beta
Classifier: Intended Audience :: Developers
Classifier: Programming Language :: Python :: 3
Classifier: License :: OSI Approved :: MIT License
Classifier: Operating System :: OS Independent
License-File: LICENSE
